b_cfn_lambda_integration/__init__.py
b_cfn_lambda_integration/lambda_integration.py
b_cfn_lambda_integration_test/integration/__init__.py
b_cfn_lambda_integration_test/unit/__init__.py
b_cfn_lambda_integration_test/unit/test_lambda_integration.py
b_cfn_lambda_integration-1.0.0.dist-info/LICENSE
b_cfn_lambda_integration-1.0.0.dist-info/METADATA
b_cfn_lambda_integration-1.0.0.dist-info/WHEEL
b_cfn_lambda_integration-1.0.0.dist-info/top_level.txt
b_cfn_lambda_integration-1.0.0.dist-info/RECORD
