Metadata-Version: 2.1
Name: b-cfn-lambda-integration
Version: 1.0.0
Summary: AWS CDK based api gateway integration resource that creates a lambda integration as cfn resource.
Home-page: https://github.com/biomapas/B.CfnLambdaIntegration.git
Author: Laimonas Sutkus
Author-email: laimonas.sutkus@biomapas.com
License: Apache License 2.0
Keywords: AWS CDK Lambda API Gateway Integration CFN
Platform: UNKNOWN
Classifier: Programming Language :: Python :: 3
Classifier: Operating System :: OS Independent
Requires-Dist: aws-cdk-lib (<3.0.0,>=2.0.0)
Requires-Dist: aws-cdk-constructs (<3.0.0,>=2.0.0)
